pydra/tasks/nipype1/__init__.py
pydra/tasks/nipype1/_version.py
pydra/tasks/nipype1/utils.py
pydra/tasks/nipype1/tests/__init__.py
pydra/tasks/nipype1/tests/test_nipype1task.py
pydra_nipype1-0.3.0.dist-info/LICENSE
pydra_nipype1-0.3.0.dist-info/WHEEL
pydra_nipype1-0.3.0.dist-info/METADATA
pydra_nipype1-0.3.0.dist-info/RECORD
