Metadata-Version: 2.1
Name: pydra-nipype1
Version: 0.3.0
Summary: Tools for importing nipype 1.x interfaces into Pydra
Keywords: pydra,nipype
Author-email: Chris Markiewicz <markiewicz@stanford.edu>
Maintainer-email: Nipype developers <neuroimaging@python.org>
Requires-Python: >=3.8
Classifier: Development Status :: 4 - Beta
Classifier: Environment :: Console
Classifier: Intended Audience :: Science/Research
Classifier: License :: OSI Approved :: Apache Software License
Classifier: Operating System :: MacOS :: MacOS X
Classifier: Operating System :: POSIX :: Linux
Classifier: Programming Language :: Python :: 3
Classifier: Topic :: Scientific/Engineering
Requires-Dist: pydra >=0.6.2
Requires-Dist: nipype
Requires-Dist: attrs >=21.3.0
Requires-Dist: black ; extra == "dev"
Requires-Dist: pre-commit ; extra == "dev"
Requires-Dist: pytest>=4.4.0 ; extra == "test"
Requires-Dist: pytest-cov ; extra == "test"
Project-URL: homepage, https://github.com/nipype/pydra-nipype1
Project-URL: repository, https://github.com/nipype/pydra-nipype1
Provides-Extra: dev
Provides-Extra: test
